Metadata-Version: 1.1
Name: django-settings-helper
Version: 1.0.3
Summary: A simple django's settings value helper
Home-page: https://github.com/chwnam/django_settings_helper
Author: changwoo
Author-email: ep6tri@hotmail.com
License: MIT
Keywords: django settings helper
Platform: UNKNOWN
Classifier: Development Status :: 3 - Alpha
Classifier: Environment :: Web Environment
Classifier: Framework :: Django
Classifier: Intended Audience :: Developers
Classifier: License :: OSI Approved :: MIT License
Classifier: Programming Language :: Python :: 3.5
